{"skeleton": {"hash": "c1aVM76ER38iiqgDEPOnqOSMr0Q", "spine": "3.6.53", "width": 266, "height": 131, "images": "./images/"}, "bones": [{"name": "root"}, {"name": "hit", "parent": "root"}, {"name": "jianzhu5", "parent": "hit"}], "slots": [{"name": "jianzhu5", "bone": "jianzhu5", "attachment": "jianzhu5"}], "skins": {"default": {"jianzhu5": {"jianzhu5": {"width": 266, "height": 131}}}}, "animations": {"animation": {"bones": {"jianzhu5": {"scale": [{"time": 0, "x": 1, "y": 1, "curve": [0.25, 0, 0.75, 1]}, {"time": 0.1, "x": 0.9, "y": 0.9, "curve": [0.25, 0, 0.75, 1]}, {"time": 0.2, "x": 1, "y": 1}]}}}}}