{"skeleton": {"hash": "/6GZSf5L/Umwqf3uMaqvClvdnR0", "spine": "3.6.53", "width": 105.09, "height": 149.11, "images": "./images/"}, "bones": [{"name": "root"}, {"name": "bone", "parent": "root", "x": 1.16, "y": -55.69, "scaleX": 0.31, "scaleY": 0.31}, {"name": "bone2", "parent": "bone", "x": 92.53, "y": 2208.71}, {"name": "body", "parent": "bone2", "length": 175.07, "rotation": 91.61, "x": -1.64, "y": 21.26}, {"name": "body2", "parent": "body", "length": 495.59, "rotation": 13.9, "x": 175.07}, {"name": "body4", "parent": "body2", "length": 252.2, "rotation": -25.21, "x": 489.29, "y": 1.75}, {"name": "hair", "parent": "body4", "x": 277.36, "y": -25.18}], "slots": [{"name": "yaosha", "bone": "bone"}, {"name": "huawei", "bone": "hair", "attachment": "huawei"}, {"name": "hair", "bone": "hair", "attachment": "hair"}], "skins": {"default": {"hair": {"hair": {"x": -13.54, "y": 32.94, "rotation": -80.29, "width": 339, "height": 481}}, "huawei": {"huawei": {"x": -103.44, "y": -49.4, "rotation": -80.29, "width": 55, "height": 44}}}}, "animations": {"animation": {"bones": {"root": {"rotate": [{"time": 0, "angle": 0, "curve": "stepped"}, {"time": 3.3333, "angle": 0}], "translate": [{"time": 0, "x": 0, "y": 0, "curve": "stepped"}, {"time": 3.3333, "x": 0, "y": 0}], "scale": [{"time": 0, "x": 1, "y": 1, "curve": "stepped"}, {"time": 3.3333, "x": 1, "y": 1}], "shear": [{"time": 0, "x": 0, "y": 0, "curve": "stepped"}, {"time": 3.3333, "x": 0, "y": 0}]}, "bone": {"rotate": [{"time": 0, "angle": 0, "curve": "stepped"}, {"time": 3.3333, "angle": 0}], "translate": [{"time": 0, "x": 0, "y": 0, "curve": "stepped"}, {"time": 3.3333, "x": 0, "y": 0}], "scale": [{"time": 0, "x": 1, "y": 1, "curve": "stepped"}, {"time": 3.3333, "x": 1, "y": 1}], "shear": [{"time": 0, "x": 0, "y": 0, "curve": "stepped"}, {"time": 3.3333, "x": 0, "y": 0}]}, "bone2": {"rotate": [{"time": 0, "angle": 0, "curve": "stepped"}, {"time": 3.3333, "angle": 0}], "translate": [{"time": 0, "x": 0, "y": 0, "curve": [0.25, 0, 0.75, 1]}, {"time": 1.6667, "x": 0, "y": 3.19, "curve": [0.25, 0, 0.75, 1]}, {"time": 3.3333, "x": 0, "y": 0}], "scale": [{"time": 0, "x": 1, "y": 1, "curve": "stepped"}, {"time": 3.3333, "x": 1, "y": 1}], "shear": [{"time": 0, "x": 0, "y": 0, "curve": "stepped"}, {"time": 3.3333, "x": 0, "y": 0}]}, "body": {"rotate": [{"time": 0, "angle": 0, "curve": "stepped"}, {"time": 3.3333, "angle": 0}], "translate": [{"time": 0, "x": 0, "y": 0, "curve": "stepped"}, {"time": 3.3333, "x": 0, "y": 0}], "scale": [{"time": 0, "x": 1, "y": 1, "curve": "stepped"}, {"time": 3.3333, "x": 1, "y": 1}], "shear": [{"time": 0, "x": 0, "y": 0, "curve": "stepped"}, {"time": 3.3333, "x": 0, "y": 0}]}, "body2": {"rotate": [{"time": 0, "angle": 0, "curve": "stepped"}, {"time": 3.3333, "angle": 0}], "translate": [{"time": 0, "x": 0, "y": 0, "curve": [0.25, 0, 0.75, 1]}, {"time": 1.6667, "x": 6.64, "y": -0.19, "curve": [0.25, 0, 0.75, 1]}, {"time": 3.3333, "x": 0, "y": 0}], "scale": [{"time": 0, "x": 1, "y": 1, "curve": "stepped"}, {"time": 3.3333, "x": 1, "y": 1}], "shear": [{"time": 0, "x": 0, "y": 0, "curve": "stepped"}, {"time": 3.3333, "x": 0, "y": 0}]}, "body4": {"rotate": [{"time": 0, "angle": 0, "curve": "stepped"}, {"time": 3.3333, "angle": 0}], "translate": [{"time": 0, "x": 0, "y": 0, "curve": "stepped"}, {"time": 3.3333, "x": 0, "y": 0}], "scale": [{"time": 0, "x": 1, "y": 1, "curve": "stepped"}, {"time": 3.3333, "x": 1, "y": 1}], "shear": [{"time": 0, "x": 0, "y": 0, "curve": "stepped"}, {"time": 3.3333, "x": 0, "y": 0}]}, "hair": {"rotate": [{"time": 0, "angle": 0, "curve": "stepped"}, {"time": 3.3333, "angle": 0}], "translate": [{"time": 0, "x": 0, "y": 0, "curve": "stepped"}, {"time": 3.3333, "x": 0, "y": 0}], "scale": [{"time": 0, "x": 1, "y": 1, "curve": "stepped"}, {"time": 3.3333, "x": 1, "y": 1}], "shear": [{"time": 0, "x": 0, "y": 0, "curve": "stepped"}, {"time": 3.3333, "x": 0, "y": 0}]}}}}}