{"skeleton": {"hash": "eVb2ctzq4J8O2xt4D9CxWQyNtHQ", "spine": "3.6.53", "width": 1485.01, "height": 1926.33, "images": ""}, "bones": [{"name": "root"}, {"name": "JT1", "parent": "root", "y": 3}, {"name": "yanquan", "parent": "JT1"}, {"name": "yanquan1", "parent": "yanquan"}, {"name": "yanquan2", "parent": "yanquan", "rotation": -45}, {"name": "yanquan3", "parent": "yanquan", "rotation": -90}, {"name": "yanquan4", "parent": "yanquan", "rotation": -135}, {"name": "yanquan5", "parent": "yanquan", "rotation": -180}, {"name": "yanquan6", "parent": "yanquan", "rotation": 135}, {"name": "yanquan7", "parent": "yanquan", "rotation": 90}, {"name": "yanquan8", "parent": "yanquan", "rotation": 45}, {"name": "yanwu", "parent": "JT1"}, {"name": "yanwu1", "parent": "yanwu", "x": -207.02, "y": 483.46}, {"name": "yanwu2", "parent": "yanwu", "x": 198.13, "y": 417.49}, {"name": "yanwu3", "parent": "yanwu", "x": -241.76, "y": -411.61}, {"name": "yanwu4", "parent": "yanwu", "x": 208.82, "y": -408.52}, {"name": "yanwu5", "parent": "yanwu", "x": -187.87, "y": 286.75}, {"name": "yanwu6", "parent": "yanwu", "x": 153.26, "y": 219.18}, {"name": "yanwu7", "parent": "yanwu", "x": -146.67, "y": -161.5}, {"name": "yanwu8", "parent": "yanwu", "x": 153.26, "y": -145.02}, {"name": "yanwu9", "parent": "yanwu"}], "slots": [{"name": "images/yanwu2", "bone": "yanwu1", "attachment": "images/yanwu"}, {"name": "images/yanwu3", "bone": "yanwu2", "attachment": "images/yanwu"}, {"name": "images/yanwu4", "bone": "yanwu3", "attachment": "images/yanwu"}, {"name": "images/yanwu5", "bone": "yanwu4", "attachment": "images/yanwu"}, {"name": "images/yanwu6", "bone": "yanwu5", "attachment": "images/yanwu"}, {"name": "images/yanwu7", "bone": "yanwu6", "attachment": "images/yanwu"}, {"name": "images/yanwu8", "bone": "yanwu7", "attachment": "images/yanwu"}, {"name": "images/yanwu9", "bone": "yanwu8", "attachment": "images/yanwu"}, {"name": "images/yanwu10", "bone": "yanwu9", "attachment": "images/yanwu"}, {"name": "images/yanwu11", "bone": "yanquan1", "attachment": "images/yanwu"}, {"name": "images/yanwu12", "bone": "yanquan2", "attachment": "images/yanwu"}, {"name": "images/yanwu13", "bone": "yanquan3", "attachment": "images/yanwu"}, {"name": "images/yanwu14", "bone": "yanquan4", "attachment": "images/yanwu"}, {"name": "images/yanwu15", "bone": "yanquan5", "attachment": "images/yanwu"}, {"name": "images/yanwu16", "bone": "yanquan6", "attachment": "images/yanwu"}, {"name": "images/yanwu17", "bone": "yanquan7", "attachment": "images/yanwu"}, {"name": "images/yanwu18", "bone": "yanquan8", "attachment": "images/yanwu"}], "skins": {"default": {"images/yanwu10": {"images/yanwu": {"rotation": -90, "width": 899, "height": 710}}, "images/yanwu11": {"images/yanwu": {"scaleX": 0.3, "scaleY": 0.3, "rotation": -0.08, "width": 899, "height": 710}}, "images/yanwu12": {"images/yanwu": {"scaleX": 0.3, "scaleY": 0.3, "rotation": -0.08, "width": 899, "height": 710}}, "images/yanwu13": {"images/yanwu": {"scaleX": 0.3, "scaleY": 0.3, "rotation": -0.08, "width": 899, "height": 710}}, "images/yanwu14": {"images/yanwu": {"scaleX": 0.3, "scaleY": 0.3, "rotation": -0.08, "width": 899, "height": 710}}, "images/yanwu15": {"images/yanwu": {"scaleX": 0.3, "scaleY": 0.3, "rotation": -0.08, "width": 899, "height": 710}}, "images/yanwu16": {"images/yanwu": {"scaleX": 0.3, "scaleY": 0.3, "rotation": -0.08, "width": 899, "height": 710}}, "images/yanwu17": {"images/yanwu": {"scaleX": 0.3, "scaleY": 0.3, "rotation": -0.08, "width": 899, "height": 710}}, "images/yanwu18": {"images/yanwu": {"scaleX": 0.3, "scaleY": 0.3, "rotation": -0.08, "width": 899, "height": 710}}, "images/yanwu2": {"images/yanwu": {"rotation": -100.96, "width": 899, "height": 710}}, "images/yanwu3": {"images/yanwu": {"rotation": -78.6, "width": 899, "height": 710}}, "images/yanwu4": {"images/yanwu": {"rotation": -82.94, "width": 899, "height": 710}}, "images/yanwu5": {"images/yanwu": {"rotation": 104.87, "width": 899, "height": 710}}, "images/yanwu6": {"images/yanwu": {"rotation": 42.28, "width": 899, "height": 710}}, "images/yanwu7": {"images/yanwu": {"rotation": 143.55, "width": 899, "height": 710}}, "images/yanwu8": {"images/yanwu": {"rotation": -57.56, "width": 899, "height": 710}}, "images/yanwu9": {"images/yanwu": {"rotation": -118.08, "width": 899, "height": 710}}}}, "events": {"guan": {}, "kai": {}}, "animations": {"guan": {"slots": {"images/yanwu2": {"color": [{"time": 0, "color": "ffffff00"}, {"time": 0.5, "color": "ffffffff", "curve": "stepped"}, {"time": 1.5, "color": "ffffffff"}]}, "images/yanwu3": {"color": [{"time": 0, "color": "ffffff00"}, {"time": 0.5, "color": "ffffffff", "curve": "stepped"}, {"time": 1.5, "color": "ffffffff"}]}, "images/yanwu4": {"color": [{"time": 0, "color": "ffffff00"}, {"time": 0.5, "color": "ffffffff", "curve": "stepped"}, {"time": 1.5, "color": "ffffffff"}]}, "images/yanwu5": {"color": [{"time": 0, "color": "ffffff00"}, {"time": 0.5, "color": "ffffffff", "curve": "stepped"}, {"time": 1.5, "color": "ffffffff"}]}, "images/yanwu6": {"color": [{"time": 0, "color": "ffffff00"}, {"time": 1.5, "color": "ffffffff"}]}, "images/yanwu7": {"color": [{"time": 0, "color": "ffffff00"}, {"time": 1.5, "color": "ffffffff"}]}, "images/yanwu8": {"color": [{"time": 0, "color": "ffffff00"}, {"time": 1.5, "color": "ffffffff"}]}, "images/yanwu9": {"color": [{"time": 0, "color": "ffffff00"}, {"time": 1.5, "color": "ffffffff"}]}, "images/yanwu10": {"color": [{"time": 0, "color": "ffffff00", "curve": "stepped"}, {"time": 0.9, "color": "ffffff00"}, {"time": 1.5, "color": "ffffffff"}]}, "images/yanwu11": {"color": [{"time": 0, "color": "ffffff00", "curve": "stepped"}, {"time": 0.5, "color": "ffffff00"}, {"time": 1, "color": "ffffffff"}, {"time": 1.5, "color": "ffffff00"}]}, "images/yanwu12": {"color": [{"time": 0, "color": "ffffff00", "curve": "stepped"}, {"time": 0.5, "color": "ffffff00"}, {"time": 1, "color": "ffffffff"}, {"time": 1.5, "color": "ffffff00"}]}, "images/yanwu13": {"color": [{"time": 0, "color": "ffffff00", "curve": "stepped"}, {"time": 0.5, "color": "ffffff00"}, {"time": 1, "color": "ffffffff"}, {"time": 1.5, "color": "ffffff00"}]}, "images/yanwu14": {"color": [{"time": 0, "color": "ffffff00", "curve": "stepped"}, {"time": 0.5, "color": "ffffff00"}, {"time": 1, "color": "ffffffff"}, {"time": 1.5, "color": "ffffff00"}]}, "images/yanwu15": {"color": [{"time": 0, "color": "ffffff00", "curve": "stepped"}, {"time": 0.5, "color": "ffffff00"}, {"time": 1, "color": "ffffffff"}, {"time": 1.5, "color": "ffffff00"}]}, "images/yanwu16": {"color": [{"time": 0, "color": "ffffff00", "curve": "stepped"}, {"time": 0.5, "color": "ffffff00"}, {"time": 1, "color": "ffffffff"}, {"time": 1.5, "color": "ffffff00"}]}, "images/yanwu17": {"color": [{"time": 0, "color": "ffffff00", "curve": "stepped"}, {"time": 0.5, "color": "ffffff00"}, {"time": 1, "color": "ffffffff"}, {"time": 1.5, "color": "ffffff00"}]}, "images/yanwu18": {"color": [{"time": 0, "color": "ffffff00", "curve": "stepped"}, {"time": 0.5, "color": "ffffff00"}, {"time": 1, "color": "ffffffff"}, {"time": 1.5, "color": "ffffff00"}]}}, "bones": {"yanwu5": {"rotate": [{"time": 0, "angle": 0, "curve": "stepped"}, {"time": 1.5, "angle": 0}], "translate": [{"time": 0, "x": -228.94, "y": -252.84}, {"time": 1.5, "x": 40.23, "y": -83.03}], "scale": [{"time": 0, "x": 1, "y": 1, "curve": "stepped"}, {"time": 1.5, "x": 1, "y": 1}]}, "yanwu8": {"rotate": [{"time": 0, "angle": 0, "curve": "stepped"}, {"time": 1.5, "angle": 0}], "translate": [{"time": 0, "x": 181.11, "y": 123.73}, {"time": 1.5, "x": 40.23, "y": -83.03}], "scale": [{"time": 0, "x": 1, "y": 1, "curve": "stepped"}, {"time": 1.5, "x": 1, "y": 1}]}, "yanwu1": {"rotate": [{"time": 0, "angle": 0, "curve": "stepped"}, {"time": 1.5, "angle": 0}], "translate": [{"time": 0, "x": -146.43, "y": 144.48}, {"time": 1.5, "x": 55.34, "y": 0}], "scale": [{"time": 0, "x": 1.992, "y": 1}, {"time": 1.5, "x": 1, "y": 1}]}, "yanquan6": {"rotate": [{"time": 0, "angle": 0, "curve": "stepped"}, {"time": 0.5, "angle": 0, "curve": "stepped"}, {"time": 1.5, "angle": 0}], "translate": [{"time": 0, "x": -284.39, "y": -282.56, "curve": "stepped"}, {"time": 0.5, "x": -284.39, "y": -282.56}, {"time": 1.5, "x": 0, "y": 0}], "scale": [{"time": 0, "x": 3, "y": 3, "curve": "stepped"}, {"time": 0.5, "x": 3, "y": 3}, {"time": 1.5, "x": 2, "y": 2}]}, "yanwu7": {"rotate": [{"time": 0, "angle": 0, "curve": "stepped"}, {"time": 1.5, "angle": 0}], "translate": [{"time": 0, "x": 126.89, "y": -369.7}, {"time": 1.5, "x": 40.23, "y": -83.03}], "scale": [{"time": 0, "x": 1, "y": 1, "curve": "stepped"}, {"time": 1.5, "x": 1, "y": 1}]}, "yanquan": {"rotate": [{"time": 0, "angle": 0, "curve": "stepped"}, {"time": 1.5, "angle": 0}], "translate": [{"time": 0, "x": 0, "y": 0, "curve": "stepped"}, {"time": 1.5, "x": 0, "y": 0}], "scale": [{"time": 0, "x": 1, "y": 1, "curve": "stepped"}, {"time": 1.5, "x": 1, "y": 1}]}, "yanwu2": {"rotate": [{"time": 0, "angle": 32.01}, {"time": 1.5, "angle": 0}], "translate": [{"time": 0, "x": 237.19, "y": 211.73}, {"time": 1.5, "x": 55.34, "y": 0}], "scale": [{"time": 0, "x": 1, "y": 3}, {"time": 1.5, "x": 1, "y": 1}]}, "yanquan1": {"rotate": [{"time": 0, "angle": 0, "curve": "stepped"}, {"time": 0.5, "angle": 0, "curve": "stepped"}, {"time": 1.5, "angle": 0}], "translate": [{"time": 0, "x": 0, "y": 423.51, "curve": "stepped"}, {"time": 0.5, "x": 0, "y": 423.51}, {"time": 1.5, "x": 0, "y": 0}], "scale": [{"time": 0, "x": 3, "y": 3, "curve": "stepped"}, {"time": 0.5, "x": 3, "y": 3}, {"time": 1.5, "x": 2, "y": 2}]}, "yanquan7": {"rotate": [{"time": 0, "angle": 0, "curve": "stepped"}, {"time": 0.5, "angle": 0, "curve": "stepped"}, {"time": 1.5, "angle": 0}], "translate": [{"time": 0, "x": -404.12, "y": 0, "curve": "stepped"}, {"time": 0.5, "x": -404.12, "y": 0}, {"time": 1.5, "x": 0, "y": 0}], "scale": [{"time": 0, "x": 3, "y": 3, "curve": "stepped"}, {"time": 0.5, "x": 3, "y": 3}, {"time": 1.5, "x": 2, "y": 2}]}, "yanquan8": {"rotate": [{"time": 0, "angle": 0, "curve": "stepped"}, {"time": 0.5, "angle": 0, "curve": "stepped"}, {"time": 1.5, "angle": 0}], "translate": [{"time": 0, "x": -235.17, "y": 293.5, "curve": "stepped"}, {"time": 0.5, "x": -235.17, "y": 293.5}, {"time": 1.5, "x": 0, "y": 0}], "scale": [{"time": 0, "x": 3, "y": 3, "curve": "stepped"}, {"time": 0.5, "x": 3, "y": 3}, {"time": 1.5, "x": 2, "y": 2}]}, "yanwu6": {"rotate": [{"time": 0, "angle": 0, "curve": "stepped"}, {"time": 1.5, "angle": 0}], "translate": [{"time": 0, "x": -125.08, "y": 335.37}, {"time": 1.5, "x": 40.23, "y": -83.03}], "scale": [{"time": 0, "x": 1, "y": 1, "curve": "stepped"}, {"time": 1.5, "x": 1, "y": 1}]}, "yanquan5": {"rotate": [{"time": 0, "angle": 0, "curve": "stepped"}, {"time": 0.5, "angle": 0, "curve": "stepped"}, {"time": 1.5, "angle": 0}], "translate": [{"time": 0, "x": 0, "y": -422.94, "curve": "stepped"}, {"time": 0.5, "x": 0, "y": -422.94}, {"time": 1.5, "x": 0, "y": 0}], "scale": [{"time": 0, "x": 3, "y": 3, "curve": "stepped"}, {"time": 0.5, "x": 3, "y": 3}, {"time": 1.5, "x": 2, "y": 2}]}, "root": {"rotate": [{"time": 0, "angle": 0, "curve": "stepped"}, {"time": 1.5, "angle": 0}], "translate": [{"time": 0, "x": 0, "y": 0, "curve": "stepped"}, {"time": 1.5, "x": 0, "y": 0}], "scale": [{"time": 0, "x": 1, "y": 1, "curve": "stepped"}, {"time": 1.5, "x": 1, "y": 1}]}, "yanquan3": {"rotate": [{"time": 0, "angle": 0, "curve": "stepped"}, {"time": 0.5, "angle": 0, "curve": "stepped"}, {"time": 1.5, "angle": 0}], "translate": [{"time": 0, "x": 421.07, "y": 0, "curve": "stepped"}, {"time": 0.5, "x": 421.07, "y": 0}, {"time": 1.5, "x": 0, "y": 0}], "scale": [{"time": 0, "x": 3, "y": 3, "curve": "stepped"}, {"time": 0.5, "x": 3, "y": 3}, {"time": 1.5, "x": 2, "y": 2}]}, "yanwu9": {"rotate": [{"time": 0, "angle": 0, "curve": "stepped"}, {"time": 1.5, "angle": 0}], "translate": [{"time": 0, "x": -15.1, "y": 0, "curve": "stepped"}, {"time": 1.5, "x": -15.1, "y": 0}], "scale": [{"time": 0, "x": 2, "y": 2, "curve": "stepped"}, {"time": 0.9, "x": 2, "y": 2}, {"time": 1.5, "x": 1.867, "y": 1.867}]}, "yanwu4": {"rotate": [{"time": 0, "angle": 0, "curve": "stepped"}, {"time": 1.5, "angle": 0}], "translate": [{"time": 0, "x": 247.15, "y": -159.42}, {"time": 1.5, "x": 55.34, "y": 0}], "scale": [{"time": 0, "x": 3, "y": 1}, {"time": 1.5, "x": 1, "y": 1}]}, "yanwu": {"rotate": [{"time": 0, "angle": 0, "curve": "stepped"}, {"time": 1.5, "angle": 0}], "translate": [{"time": 0, "x": 0, "y": 0, "curve": "stepped"}, {"time": 1.5, "x": 0, "y": 0}], "scale": [{"time": 0, "x": 1, "y": 1, "curve": "stepped"}, {"time": 1.5, "x": 1, "y": 1}]}, "JT1": {"rotate": [{"time": 0, "angle": 0, "curve": "stepped"}, {"time": 1.5, "angle": 0}], "translate": [{"time": 0, "x": 0, "y": -3, "curve": "stepped"}, {"time": 1.5, "x": 0, "y": -3}], "scale": [{"time": 0, "x": 1, "y": 1, "curve": "stepped"}, {"time": 1.5, "x": 1, "y": 1}]}, "yanquan4": {"rotate": [{"time": 0, "angle": 0, "curve": "stepped"}, {"time": 0.5, "angle": 0, "curve": "stepped"}, {"time": 1.5, "angle": 0}], "translate": [{"time": 0, "x": 258.87, "y": -317.2, "curve": "stepped"}, {"time": 0.5, "x": 258.87, "y": -317.2}, {"time": 1.5, "x": 0, "y": 0}], "scale": [{"time": 0, "x": 3, "y": 3, "curve": "stepped"}, {"time": 0.5, "x": 3, "y": 3}, {"time": 1.5, "x": 2, "y": 2}]}, "yanquan2": {"rotate": [{"time": 0, "angle": 0, "curve": "stepped"}, {"time": 0.5, "angle": 0, "curve": "stepped"}, {"time": 1.5, "angle": 0}], "translate": [{"time": 0, "x": 278.92, "y": 306.26, "curve": "stepped"}, {"time": 0.5, "x": 278.92, "y": 306.26}, {"time": 1.5, "x": 0, "y": 0}], "scale": [{"time": 0, "x": 3, "y": 3, "curve": "stepped"}, {"time": 0.5, "x": 3, "y": 3}, {"time": 1.5, "x": 2, "y": 2}]}, "yanwu3": {"rotate": [{"time": 0, "angle": 30.23}, {"time": 1.5, "angle": 0}], "translate": [{"time": 0, "x": -156.39, "y": -132.02}, {"time": 1.5, "x": 55.34, "y": 0}], "scale": [{"time": 0, "x": 1, "y": 3}, {"time": 1.5, "x": 1, "y": 1}]}}, "events": [{"time": 1.5, "name": "guan"}]}, "kai": {"slots": {"images/yanwu2": {"color": [{"time": 0, "color": "ffffffff", "curve": "stepped"}, {"time": 1, "color": "ffffffff"}, {"time": 1.5, "color": "ffffff00"}]}, "images/yanwu3": {"color": [{"time": 0, "color": "ffffffff", "curve": "stepped"}, {"time": 1, "color": "ffffffff"}, {"time": 1.5, "color": "ffffff00"}]}, "images/yanwu4": {"color": [{"time": 0, "color": "ffffffff", "curve": "stepped"}, {"time": 1, "color": "ffffffff"}, {"time": 1.5, "color": "ffffff00"}]}, "images/yanwu5": {"color": [{"time": 0, "color": "ffffffff", "curve": "stepped"}, {"time": 1, "color": "ffffffff"}, {"time": 1.5, "color": "ffffff00"}]}, "images/yanwu6": {"color": [{"time": 0, "color": "ffffffff"}, {"time": 1.5, "color": "ffffff00"}]}, "images/yanwu7": {"color": [{"time": 0, "color": "ffffffff"}, {"time": 1.5, "color": "ffffff00"}]}, "images/yanwu8": {"color": [{"time": 0, "color": "ffffffff"}, {"time": 1.5, "color": "ffffff00"}]}, "images/yanwu9": {"color": [{"time": 0, "color": "ffffffff"}, {"time": 1.5, "color": "ffffff00"}]}, "images/yanwu10": {"color": [{"time": 0, "color": "ffffffff"}, {"time": 0.6, "color": "ffffff00", "curve": "stepped"}, {"time": 1.5, "color": "ffffff00"}]}, "images/yanwu11": {"color": [{"time": 0, "color": "ffffff00", "curve": [0.386, 0.5, 0.75, 1]}, {"time": 0.5, "color": "ffffffff"}, {"time": 1, "color": "ffffff00", "curve": "stepped"}, {"time": 1.5, "color": "ffffff00"}]}, "images/yanwu12": {"color": [{"time": 0, "color": "ffffff00", "curve": [0.386, 0.5, 0.75, 1]}, {"time": 0.5, "color": "ffffffff"}, {"time": 1, "color": "ffffff00", "curve": "stepped"}, {"time": 1.5, "color": "ffffff00"}]}, "images/yanwu13": {"color": [{"time": 0, "color": "ffffff00", "curve": [0.386, 0.5, 0.75, 1]}, {"time": 0.5, "color": "ffffffff"}, {"time": 1, "color": "ffffff00", "curve": "stepped"}, {"time": 1.5, "color": "ffffff00"}]}, "images/yanwu14": {"color": [{"time": 0, "color": "ffffff00", "curve": [0.386, 0.5, 0.75, 1]}, {"time": 0.5, "color": "ffffffff"}, {"time": 1, "color": "ffffff00", "curve": "stepped"}, {"time": 1.5, "color": "ffffff00"}]}, "images/yanwu15": {"color": [{"time": 0, "color": "ffffff00", "curve": [0.386, 0.5, 0.75, 1]}, {"time": 0.5, "color": "ffffffff"}, {"time": 1, "color": "ffffff00", "curve": "stepped"}, {"time": 1.5, "color": "ffffff00"}]}, "images/yanwu16": {"color": [{"time": 0, "color": "ffffff00", "curve": [0.386, 0.5, 0.75, 1]}, {"time": 0.5, "color": "ffffffff"}, {"time": 1, "color": "ffffff00", "curve": "stepped"}, {"time": 1.5, "color": "ffffff00"}]}, "images/yanwu17": {"color": [{"time": 0, "color": "ffffff00", "curve": [0.386, 0.5, 0.75, 1]}, {"time": 0.5, "color": "ffffffff"}, {"time": 1, "color": "ffffff00", "curve": "stepped"}, {"time": 1.5, "color": "ffffff00"}]}, "images/yanwu18": {"color": [{"time": 0, "color": "ffffff00", "curve": [0.386, 0.5, 0.75, 1]}, {"time": 0.5, "color": "ffffffff"}, {"time": 1, "color": "ffffff00", "curve": "stepped"}, {"time": 1.5, "color": "ffffff00"}]}}, "bones": {"yanwu1": {"rotate": [{"time": 0, "angle": 0, "curve": "stepped"}, {"time": 1.5, "angle": 0}], "translate": [{"time": 0, "x": 55.34, "y": 0}, {"time": 1.5, "x": -146.43, "y": 144.48}], "scale": [{"time": 0, "x": 1, "y": 1}, {"time": 1.5, "x": 1.992, "y": 1}]}, "yanwu2": {"rotate": [{"time": 0, "angle": 0}, {"time": 1.5, "angle": 32.01}], "translate": [{"time": 0, "x": 55.34, "y": 0}, {"time": 1.5, "x": 237.19, "y": 211.73}], "scale": [{"time": 0, "x": 1, "y": 1}, {"time": 1.5, "x": 1, "y": 3}]}, "yanwu3": {"rotate": [{"time": 0, "angle": 0}, {"time": 1.5, "angle": 30.23}], "translate": [{"time": 0, "x": 55.34, "y": 0}, {"time": 1.5, "x": -156.39, "y": -132.02}], "scale": [{"time": 0, "x": 1, "y": 1}, {"time": 1.5, "x": 1, "y": 3}]}, "yanwu4": {"rotate": [{"time": 0, "angle": 0, "curve": "stepped"}, {"time": 1.5, "angle": 0}], "translate": [{"time": 0, "x": 55.34, "y": 0}, {"time": 1.5, "x": 247.15, "y": -159.42}], "scale": [{"time": 0, "x": 1, "y": 1}, {"time": 1.5, "x": 3, "y": 1}]}, "yanwu5": {"rotate": [{"time": 0, "angle": 0, "curve": "stepped"}, {"time": 1.5, "angle": 0}], "translate": [{"time": 0, "x": 40.23, "y": -83.03}, {"time": 1.5, "x": -228.94, "y": -252.84}], "scale": [{"time": 0, "x": 1, "y": 1, "curve": "stepped"}, {"time": 1.5, "x": 1, "y": 1}]}, "yanwu6": {"rotate": [{"time": 0, "angle": 0, "curve": "stepped"}, {"time": 1.5, "angle": 0}], "translate": [{"time": 0, "x": 40.23, "y": -83.03}, {"time": 1.5, "x": -125.08, "y": 335.37}], "scale": [{"time": 0, "x": 1, "y": 1, "curve": "stepped"}, {"time": 1.5, "x": 1, "y": 1}]}, "yanwu7": {"rotate": [{"time": 0, "angle": 0, "curve": "stepped"}, {"time": 1.5, "angle": 0}], "translate": [{"time": 0, "x": 40.23, "y": -83.03}, {"time": 1.5, "x": 126.89, "y": -369.7}], "scale": [{"time": 0, "x": 1, "y": 1, "curve": "stepped"}, {"time": 1.5, "x": 1, "y": 1}]}, "yanwu8": {"rotate": [{"time": 0, "angle": 0, "curve": "stepped"}, {"time": 1.5, "angle": 0}], "translate": [{"time": 0, "x": 40.23, "y": -83.03}, {"time": 1.5, "x": 181.11, "y": 123.73}], "scale": [{"time": 0, "x": 1, "y": 1, "curve": "stepped"}, {"time": 1.5, "x": 1, "y": 1}]}, "yanwu9": {"rotate": [{"time": 0, "angle": 0, "curve": "stepped"}, {"time": 1.5, "angle": 0}], "translate": [{"time": 0, "x": -15.1, "y": 0, "curve": "stepped"}, {"time": 1.5, "x": -15.1, "y": 0}], "scale": [{"time": 0, "x": 1.867, "y": 1.867, "curve": [0.257, 0.45, 0.75, 1]}, {"time": 0.6, "x": 2, "y": 2, "curve": "stepped"}, {"time": 1.5, "x": 2, "y": 2}]}, "yanquan8": {"rotate": [{"time": 0, "angle": 0, "curve": "stepped"}, {"time": 1, "angle": 0, "curve": "stepped"}, {"time": 1.5, "angle": 0}], "translate": [{"time": 0, "x": 0, "y": 0, "curve": [0.386, 0.5, 0.75, 1]}, {"time": 1, "x": -235.17, "y": 293.5, "curve": "stepped"}, {"time": 1.5, "x": -235.17, "y": 293.5}], "scale": [{"time": 0, "x": 2, "y": 2, "curve": [0.386, 0.5, 0.75, 1]}, {"time": 1, "x": 3, "y": 3, "curve": "stepped"}, {"time": 1.5, "x": 3, "y": 3}]}, "yanquan7": {"rotate": [{"time": 0, "angle": 0, "curve": "stepped"}, {"time": 1, "angle": 0, "curve": "stepped"}, {"time": 1.5, "angle": 0}], "translate": [{"time": 0, "x": 0, "y": 0, "curve": [0.386, 0.5, 0.75, 1]}, {"time": 1, "x": -404.12, "y": 0, "curve": "stepped"}, {"time": 1.5, "x": -404.12, "y": 0}], "scale": [{"time": 0, "x": 2, "y": 2, "curve": [0.386, 0.5, 0.75, 1]}, {"time": 1, "x": 3, "y": 3, "curve": "stepped"}, {"time": 1.5, "x": 3, "y": 3}]}, "yanquan6": {"rotate": [{"time": 0, "angle": 0, "curve": "stepped"}, {"time": 1, "angle": 0, "curve": "stepped"}, {"time": 1.5, "angle": 0}], "translate": [{"time": 0, "x": 0, "y": 0, "curve": [0.386, 0.5, 0.75, 1]}, {"time": 1, "x": -284.39, "y": -282.56, "curve": "stepped"}, {"time": 1.5, "x": -284.39, "y": -282.56}], "scale": [{"time": 0, "x": 2, "y": 2, "curve": [0.386, 0.5, 0.75, 1]}, {"time": 1, "x": 3, "y": 3, "curve": "stepped"}, {"time": 1.5, "x": 3, "y": 3}]}, "yanquan5": {"rotate": [{"time": 0, "angle": 0, "curve": "stepped"}, {"time": 1, "angle": 0, "curve": "stepped"}, {"time": 1.5, "angle": 0}], "translate": [{"time": 0, "x": 0, "y": 0, "curve": [0.386, 0.5, 0.75, 1]}, {"time": 1, "x": 0, "y": -422.94, "curve": "stepped"}, {"time": 1.5, "x": 0, "y": -422.94}], "scale": [{"time": 0, "x": 2, "y": 2, "curve": [0.386, 0.5, 0.75, 1]}, {"time": 1, "x": 3, "y": 3, "curve": "stepped"}, {"time": 1.5, "x": 3, "y": 3}]}, "yanquan4": {"rotate": [{"time": 0, "angle": 0, "curve": "stepped"}, {"time": 1, "angle": 0, "curve": "stepped"}, {"time": 1.5, "angle": 0}], "translate": [{"time": 0, "x": 0, "y": 0, "curve": [0.386, 0.5, 0.75, 1]}, {"time": 1, "x": 258.87, "y": -317.2, "curve": "stepped"}, {"time": 1.5, "x": 258.87, "y": -317.2}], "scale": [{"time": 0, "x": 2, "y": 2, "curve": [0.386, 0.5, 0.75, 1]}, {"time": 1, "x": 3, "y": 3, "curve": "stepped"}, {"time": 1.5, "x": 3, "y": 3}]}, "yanquan3": {"rotate": [{"time": 0, "angle": 0, "curve": "stepped"}, {"time": 1, "angle": 0, "curve": "stepped"}, {"time": 1.5, "angle": 0}], "translate": [{"time": 0, "x": 0, "y": 0, "curve": [0.386, 0.5, 0.75, 1]}, {"time": 1, "x": 421.07, "y": 0, "curve": "stepped"}, {"time": 1.5, "x": 421.07, "y": 0}], "scale": [{"time": 0, "x": 2, "y": 2, "curve": [0.386, 0.5, 0.75, 1]}, {"time": 1, "x": 3, "y": 3, "curve": "stepped"}, {"time": 1.5, "x": 3, "y": 3}]}, "yanquan1": {"rotate": [{"time": 0, "angle": 0, "curve": "stepped"}, {"time": 1, "angle": 0, "curve": "stepped"}, {"time": 1.5, "angle": 0}], "translate": [{"time": 0, "x": 0, "y": 0, "curve": [0.386, 0.5, 0.75, 1]}, {"time": 1, "x": 0, "y": 423.51, "curve": "stepped"}, {"time": 1.5, "x": 0, "y": 423.51}], "scale": [{"time": 0, "x": 2, "y": 2, "curve": [0.386, 0.5, 0.75, 1]}, {"time": 1, "x": 3, "y": 3, "curve": "stepped"}, {"time": 1.5, "x": 3, "y": 3}]}, "yanquan2": {"rotate": [{"time": 0, "angle": 0, "curve": "stepped"}, {"time": 1, "angle": 0, "curve": "stepped"}, {"time": 1.5, "angle": 0}], "translate": [{"time": 0, "x": 0, "y": 0, "curve": [0.386, 0.5, 0.75, 1]}, {"time": 1, "x": 278.92, "y": 306.26, "curve": "stepped"}, {"time": 1.5, "x": 278.92, "y": 306.26}], "scale": [{"time": 0, "x": 2, "y": 2, "curve": [0.386, 0.5, 0.75, 1]}, {"time": 1, "x": 3, "y": 3, "curve": "stepped"}, {"time": 1.5, "x": 3, "y": 3}]}, "JT1": {"rotate": [{"time": 0, "angle": 0, "curve": "stepped"}, {"time": 1.5, "angle": 0}], "translate": [{"time": 0, "x": 0, "y": -3, "curve": "stepped"}, {"time": 1.5, "x": 0, "y": -3}], "scale": [{"time": 0, "x": 1, "y": 1, "curve": "stepped"}, {"time": 1.5, "x": 1, "y": 1}]}, "root": {"rotate": [{"time": 0, "angle": 0, "curve": "stepped"}, {"time": 1.5, "angle": 0}], "translate": [{"time": 0, "x": 0, "y": 0, "curve": "stepped"}, {"time": 1.5, "x": 0, "y": 0}], "scale": [{"time": 0, "x": 1, "y": 1, "curve": "stepped"}, {"time": 1.5, "x": 1, "y": 1}]}, "yanwu": {"rotate": [{"time": 0, "angle": 0, "curve": "stepped"}, {"time": 1.5, "angle": 0}], "translate": [{"time": 0, "x": 0, "y": 0, "curve": "stepped"}, {"time": 1.5, "x": 0, "y": 0}], "scale": [{"time": 0, "x": 1, "y": 1, "curve": "stepped"}, {"time": 1.5, "x": 1, "y": 1}]}, "yanquan": {"rotate": [{"time": 0, "angle": 0, "curve": "stepped"}, {"time": 1.5, "angle": 0}], "translate": [{"time": 0, "x": 0, "y": 0, "curve": "stepped"}, {"time": 1.5, "x": 0, "y": 0}], "scale": [{"time": 0, "x": 1, "y": 1, "curve": "stepped"}, {"time": 1.5, "x": 1, "y": 1}]}}, "events": [{"time": 1.5, "name": "kai"}]}}}